{
  "meta": {
    "source": "Meta Ads export (Engagement + Traffic only) · via Import tab",
    "generatedAt": "2026-06-26T06:34:25Z",
    "currency": "INR",
    "note": "Lead campaigns excluded; duplicate rows removed automatically."
  },
  "summary": {
    "pieces": 75,
    "boosted": 75,
    "totalSpend": 28832.84,
    "spendTraffic": 6372.19,
    "spendEngagement": 22460.65,
    "avgCPV": 0.025538,
    "avgCPE": 0.257714,
    "profitable": 38,
    "brokeEven": 22,
    "lossMaking": 15
  },
  "pieces": [
    {
      "title": "Proposition  Static",
      "format": "Static",
      "bucket": "Static",
      "objective": "Engagement",
      "date": "2025-08-09",
      "month": "Aug 2025",
      "boosted": true,
      "spend": 1434.34,
      "reach": 66054.0,
      "views": 0.0,
      "engagements": 683.0,
      "saves": 6.0,
      "shares": 0.0,
      "follows": 0.0,
      "likes": 36.0,
      "comments": 0.0,
      "status": "Inactive",
      "cpv": null,
      "cpe": 2.100059,
      "saveRate": 9.1e-05,
      "shareRate": 0.0,
      "hookRate": null,
      "engRate": 0.01034,
      "image": null,
      "verdict": "Loss-making"
    },
    {
      "title": "Expert Opinion_3 Tips Before Installing Motorised Curtains",
      "format": "Reel",
      "bucket": "Expert Opinion",
      "objective": "Engagement",
      "date": "2026-05-11",
      "month": "May 2026",
      "boosted": true,
      "spend": 1322.28,
      "reach": 26447.0,
      "views": 46814.0,
      "engagements": 6078.0,
      "saves": 1.0,
      "shares": 24.0,
      "follows": 0.0,
      "likes": 3212.0,
      "comments": 1.0,
      "status": "Inactive",
      "cpv": 0.028245,
      "cpe": 0.217552,
      "saveRate": 3.8e-05,
      "shareRate": 0.000907,
      "hookRate": 0.107347,
      "engRate": 0.229818,
      "image": null,
      "verdict": "Broke even"
    },
    {
      "title": "Testimonial_Sangeeta Mandal",
      "format": "Reel",
      "bucket": "Testimonial",
      "objective": "Engagement",
      "date": "2026-06-03",
      "month": "Jun 2026",
      "boosted": true,
      "spend": 1013.73,
      "reach": 28641.0,
      "views": 40710.0,
      "engagements": 5035.0,
      "saves": 1.0,
      "shares": 18.0,
      "follows": 0.0,
      "likes": 2935.0,
      "comments": 3.0,
      "status": "Inactive",
      "cpv": 0.024901,
      "cpe": 0.201337,
      "saveRate": 3.5e-05,
      "shareRate": 0.000628,
      "hookRate": 0.072518,
      "engRate": 0.175797,
      "image": null,
      "verdict": "Profitable"
    },
    {
      "title": "Expert Opinion_Readymade vs Customised Curtains",
      "format": "Reel",
      "bucket": "Expert Opinion",
      "objective": "Engagement",
      "date": "2026-06-03",
      "month": "Jun 2026",
      "boosted": true,
      "spend": 990.11,
      "reach": 27679.0,
      "views": 41693.0,
      "engagements": 9180.0,
      "saves": 3.0,
      "shares": 16.0,
      "follows": 0.0,
      "likes": 2446.0,
      "comments": 2.0,
      "status": "Inactive",
      "cpv": 0.023748,
      "cpe": 0.107855,
      "saveRate": 0.000108,
      "shareRate": 0.000578,
      "hookRate": 0.235955,
      "engRate": 0.331659,
      "image": null,
      "verdict": "Profitable"
    },
    {
      "title": "Expert Opinion_Dark Vs Light Curtains",
      "format": "Reel",
      "bucket": "Expert Opinion",
      "objective": "Engagement",
      "date": "2026-05-28",
      "month": "May 2026",
      "boosted": true,
      "spend": 989.28,
      "reach": 24835.0,
      "views": 40104.0,
      "engagements": 5565.0,
      "saves": 2.0,
      "shares": 17.0,
      "follows": 0.0,
      "likes": 2914.0,
      "comments": 2.0,
      "status": "Inactive",
      "cpv": 0.024668,
      "cpe": 0.177768,
      "saveRate": 8.1e-05,
      "shareRate": 0.000685,
      "hookRate": 0.104852,
      "engRate": 0.224079,
      "image": null,
      "verdict": "Profitable"
    },
    {
      "title": "Expert Opinion_Rods Vs Pelemets",
      "format": "Reel",
      "bucket": "Expert Opinion",
      "objective": "Engagement",
      "date": "2026-05-17",
      "month": "May 2026",
      "boosted": true,
      "spend": 955.96,
      "reach": 35389.0,
      "views": 42598.0,
      "engagements": 6079.0,
      "saves": 3.0,
      "shares": 17.0,
      "follows": 3.0,
      "likes": 1777.0,
      "comments": 2.0,
      "status": "Inactive",
      "cpv": 0.022441,
      "cpe": 0.157256,
      "saveRate": 8.5e-05,
      "shareRate": 0.00048,
      "hookRate": 0.116364,
      "engRate": 0.171777,
      "image": null,
      "verdict": "Profitable"
    },
    {
      "title": "Topical_Festive Ready Curtains",
      "format": "Reel",
      "bucket": "Topical",
      "objective": "Engagement",
      "date": "2025-10-07",
      "month": "Oct 2025",
      "boosted": true,
      "spend": 898.42,
      "reach": 48999.0,
      "views": 49479.0,
      "engagements": 14057.0,
      "saves": 1.0,
      "shares": 3.0,
      "follows": 0.0,
      "likes": 8590.0,
      "comments": 1.0,
      "status": "Inactive",
      "cpv": 0.018158,
      "cpe": 0.063913,
      "saveRate": 2e-05,
      "shareRate": 6.1e-05,
      "hookRate": 0.111125,
      "engRate": 0.286883,
      "image": null,
      "verdict": "Profitable"
    },
    {
      "title": "Topical_Gudi Padwa",
      "format": "Reel",
      "bucket": "Topical",
      "objective": "Engagement",
      "date": "2026-03-01",
      "month": "Mar 2026",
      "boosted": true,
      "spend": 872.52,
      "reach": 33160.0,
      "views": 49547.0,
      "engagements": 8346.0,
      "saves": 4.0,
      "shares": 31.0,
      "follows": 0.0,
      "likes": 3626.0,
      "comments": 0.0,
      "status": "Inactive",
      "cpv": 0.01761,
      "cpe": 0.104543,
      "saveRate": 0.000121,
      "shareRate": 0.000935,
      "hookRate": 0.140229,
      "engRate": 0.251689,
      "image": null,
      "verdict": "Profitable"
    },
    {
      "title": "Expert Opinion: Difference Between Blackouts and Dimouts",
      "format": "Reel",
      "bucket": "Expert Opinion",
      "objective": "Engagement",
      "date": "2025-10-29",
      "month": "Oct 2025",
      "boosted": true,
      "spend": 800.15,
      "reach": 57151.0,
      "views": 60658.0,
      "engagements": 22991.0,
      "saves": 1.0,
      "shares": 1.0,
      "follows": 0.0,
      "likes": 8791.0,
      "comments": 2.0,
      "status": "Inactive",
      "cpv": 0.013191,
      "cpe": 0.034803,
      "saveRate": 1.7e-05,
      "shareRate": 1.7e-05,
      "hookRate": 0.247712,
      "engRate": 0.402285,
      "image": null,
      "verdict": "Profitable"
    },
    {
      "title": "Main Contest Reel",
      "format": "Reel",
      "bucket": "Proposition",
      "objective": "Engagement",
      "date": "2025-10-04",
      "month": "Oct 2025",
      "boosted": true,
      "spend": 682.85,
      "reach": 43464.0,
      "views": 48668.0,
      "engagements": 19830.0,
      "saves": 0.0,
      "shares": 1.0,
      "follows": 0.0,
      "likes": 3320.0,
      "comments": 0.0,
      "status": "Inactive",
      "cpv": 0.014031,
      "cpe": 0.034435,
      "saveRate": 0.0,
      "shareRate": 2.3e-05,
      "hookRate": 0.37944,
      "engRate": 0.45624,
      "image": null,
      "verdict": "Profitable"
    },
    {
      "title": "Expert Opinion: Kinds of Pleats",
      "format": "Reel",
      "bucket": "Expert Opinion",
      "objective": "Engagement",
      "date": "2025-10-29",
      "month": "Oct 2025",
      "boosted": true,
      "spend": 649.66,
      "reach": 40090.0,
      "views": 44375.0,
      "engagements": 18195.0,
      "saves": 0.0,
      "shares": 11.0,
      "follows": 0.0,
      "likes": 5795.0,
      "comments": 0.0,
      "status": "Inactive",
      "cpv": 0.01464,
      "cpe": 0.035705,
      "saveRate": 0.0,
      "shareRate": 0.000274,
      "hookRate": 0.308207,
      "engRate": 0.453854,
      "image": null,
      "verdict": "Profitable"
    },
    {
      "title": "Expert Opinion: Make room look bigger",
      "format": "Reel",
      "bucket": "Expert Opinion",
      "objective": "Engagement",
      "date": "2025-10-29",
      "month": "Oct 2025",
      "boosted": true,
      "spend": 640.53,
      "reach": 46889.0,
      "views": 48942.0,
      "engagements": 18953.0,
      "saves": 0.0,
      "shares": 5.0,
      "follows": 1.0,
      "likes": 6812.0,
      "comments": 1.0,
      "status": "Inactive",
      "cpv": 0.013088,
      "cpe": 0.033796,
      "saveRate": 0.0,
      "shareRate": 0.000107,
      "hookRate": 0.258461,
      "engRate": 0.40421,
      "image": null,
      "verdict": "Profitable"
    },
    {
      "title": "Proposition_Main Video",
      "format": "Reel",
      "bucket": "Proposition",
      "objective": "Engagement",
      "date": "2025-08-14",
      "month": "Aug 2025",
      "boosted": true,
      "spend": 551.54,
      "reach": 14661.0,
      "views": 23077.0,
      "engagements": 4345.0,
      "saves": 0.0,
      "shares": 0.0,
      "follows": 0.0,
      "likes": 35.0,
      "comments": 0.0,
      "status": "Inactive",
      "cpv": 0.0239,
      "cpe": 0.126937,
      "saveRate": 0.0,
      "shareRate": 0.0,
      "hookRate": 0.262601,
      "engRate": 0.296365,
      "image": null,
      "verdict": "Profitable"
    },
    {
      "title": "Testimonial_Kedar Lele",
      "format": "Reel",
      "bucket": "Testimonial",
      "objective": "Engagement",
      "date": "2026-05-06",
      "month": "May 2026",
      "boosted": true,
      "spend": 532.86,
      "reach": 8982.0,
      "views": 12284.0,
      "engagements": 1373.0,
      "saves": 0.0,
      "shares": 4.0,
      "follows": 0.0,
      "likes": 858.0,
      "comments": 0.0,
      "status": "Inactive",
      "cpv": 0.043378,
      "cpe": 0.388099,
      "saveRate": 0.0,
      "shareRate": 0.000445,
      "hookRate": 0.056892,
      "engRate": 0.152861,
      "image": "images/Testimonial_Kedar%20Lele.png",
      "verdict": "Loss-making"
    },
    {
      "title": "Testimonial_Vipul.Lakme",
      "format": "Reel",
      "bucket": "Testimonial",
      "objective": "Engagement",
      "date": "2026-03-26",
      "month": "Mar 2026",
      "boosted": true,
      "spend": 517.15,
      "reach": 14578.0,
      "views": 20983.0,
      "engagements": 2188.0,
      "saves": 1.0,
      "shares": 10.0,
      "follows": 0.0,
      "likes": 1305.0,
      "comments": 0.0,
      "status": "Inactive",
      "cpv": 0.024646,
      "cpe": 0.236357,
      "saveRate": 6.9e-05,
      "shareRate": 0.000686,
      "hookRate": 0.059405,
      "engRate": 0.150089,
      "image": "images/Testimonial_Vipul.png",
      "verdict": "Profitable"
    },
    {
      "title": "Testimonial_Bindiya",
      "format": "Reel",
      "bucket": "Testimonial",
      "objective": "Engagement",
      "date": "2026-05-11",
      "month": "May 2026",
      "boosted": true,
      "spend": 514.32,
      "reach": 10789.0,
      "views": 15562.0,
      "engagements": 2043.0,
      "saves": 0.0,
      "shares": 9.0,
      "follows": 0.0,
      "likes": 1271.0,
      "comments": 0.0,
      "status": "Inactive",
      "cpv": 0.03305,
      "cpe": 0.251747,
      "saveRate": 0.0,
      "shareRate": 0.000834,
      "hookRate": 0.07072,
      "engRate": 0.18936,
      "image": "images/Testimonial_Bindiya.png",
      "verdict": "Broke even"
    },
    {
      "title": "Testimonial_Sowmya",
      "format": "Reel",
      "bucket": "Testimonial",
      "objective": "Engagement",
      "date": "2026-03-26",
      "month": "Mar 2026",
      "boosted": true,
      "spend": 505.58,
      "reach": 16789.0,
      "views": 25564.0,
      "engagements": 2052.0,
      "saves": 1.0,
      "shares": 2.0,
      "follows": 0.0,
      "likes": 1093.0,
      "comments": 0.0,
      "status": "Inactive",
      "cpv": 0.019777,
      "cpe": 0.246384,
      "saveRate": 6e-05,
      "shareRate": 0.000119,
      "hookRate": 0.056763,
      "engRate": 0.122223,
      "image": "images/Sowmya%20Thumbnail.png",
      "verdict": "Profitable"
    },
    {
      "title": "Propostion_Main Video",
      "format": "Reel",
      "bucket": "Proposition",
      "objective": "Engagement",
      "date": "2025-08-14",
      "month": "Aug 2025",
      "boosted": true,
      "spend": 504.78,
      "reach": 15558.0,
      "views": 24636.0,
      "engagements": 4191.0,
      "saves": 1.0,
      "shares": 0.0,
      "follows": 0.0,
      "likes": 34.0,
      "comments": 0.0,
      "status": "Inactive",
      "cpv": 0.02049,
      "cpe": 0.120444,
      "saveRate": 6.4e-05,
      "shareRate": 0.0,
      "hookRate": 0.240262,
      "engRate": 0.269379,
      "image": null,
      "verdict": "Profitable"
    },
    {
      "title": "Testimonial_Tanushka",
      "format": "Reel",
      "bucket": "Testimonial",
      "objective": "Engagement",
      "date": "2026-01-28",
      "month": "Jan 2026",
      "boosted": true,
      "spend": 486.69,
      "reach": 23152.0,
      "views": 23333.0,
      "engagements": 3012.0,
      "saves": 1.0,
      "shares": 2.0,
      "follows": 0.0,
      "likes": 1944.0,
      "comments": 1.0,
      "status": "Inactive",
      "cpv": 0.020858,
      "cpe": 0.161584,
      "saveRate": 4.3e-05,
      "shareRate": 8.6e-05,
      "hookRate": 0.045439,
      "engRate": 0.130097,
      "image": "images/Testimonial_Tanushka.png",
      "verdict": "Profitable"
    },
    {
      "title": "Testimonial_Dr.Somesh",
      "format": "Reel",
      "bucket": "Testimonial",
      "objective": "Engagement",
      "date": "2026-01-28",
      "month": "Jan 2026",
      "boosted": true,
      "spend": 478.81,
      "reach": 19375.0,
      "views": 20482.0,
      "engagements": 2696.0,
      "saves": 1.0,
      "shares": 1.0,
      "follows": 0.0,
      "likes": 1767.0,
      "comments": 0.0,
      "status": "Inactive",
      "cpv": 0.023377,
      "cpe": 0.1776,
      "saveRate": 5.2e-05,
      "shareRate": 5.2e-05,
      "hookRate": 0.047432,
      "engRate": 0.139148,
      "image": "images/Testimonial_Dr.Somesh.png",
      "verdict": "Profitable"
    },
    {
      "title": "Expert Opinion_Spot Pricing",
      "format": "Reel",
      "bucket": "Expert Opinion",
      "objective": "Engagement",
      "date": "2026-01-28",
      "month": "Jan 2026",
      "boosted": true,
      "spend": 472.99,
      "reach": 22328.0,
      "views": 24945.0,
      "engagements": 4571.0,
      "saves": 0.0,
      "shares": 10.0,
      "follows": 0.0,
      "likes": 2780.0,
      "comments": 0.0,
      "status": "Inactive",
      "cpv": 0.018961,
      "cpe": 0.103476,
      "saveRate": 0.0,
      "shareRate": 0.000448,
      "hookRate": 0.079317,
      "engRate": 0.204721,
      "image": null,
      "verdict": "Profitable"
    },
    {
      "title": "Proposition_Shorter Version.V2",
      "format": "Reel",
      "bucket": "Proposition",
      "objective": "Engagement",
      "date": "2026-01-28",
      "month": "Jan 2026",
      "boosted": true,
      "spend": 468.51,
      "reach": 23223.0,
      "views": 25085.0,
      "engagements": 3851.0,
      "saves": 0.0,
      "shares": 0.0,
      "follows": 0.0,
      "likes": 2034.0,
      "comments": 0.0,
      "status": "Inactive",
      "cpv": 0.018677,
      "cpe": 0.121659,
      "saveRate": 0.0,
      "shareRate": 0.0,
      "hookRate": 0.077983,
      "engRate": 0.165827,
      "image": null,
      "verdict": "Profitable"
    },
    {
      "title": "Testimonial_Pradyuman",
      "format": "Reel",
      "bucket": "Testimonial",
      "objective": "Engagement",
      "date": "2026-01-28",
      "month": "Jan 2026",
      "boosted": true,
      "spend": 468.33,
      "reach": 26370.0,
      "views": 28594.0,
      "engagements": 3900.0,
      "saves": 0.0,
      "shares": 4.0,
      "follows": 0.0,
      "likes": 2225.0,
      "comments": 2.0,
      "status": "Inactive",
      "cpv": 0.016379,
      "cpe": 0.120085,
      "saveRate": 0.0,
      "shareRate": 0.000152,
      "hookRate": 0.062799,
      "engRate": 0.147895,
      "image": "images/Testimonial_Pradyuman.png",
      "verdict": "Profitable"
    },
    {
      "title": "Proposition_Shorter Version.V1",
      "format": "Reel",
      "bucket": "Proposition",
      "objective": "Engagement",
      "date": "2026-01-28",
      "month": "Jan 2026",
      "boosted": true,
      "spend": 463.39,
      "reach": 20296.0,
      "views": 21177.0,
      "engagements": 2450.0,
      "saves": 0.0,
      "shares": 2.0,
      "follows": 0.0,
      "likes": 1506.0,
      "comments": 0.0,
      "status": "Inactive",
      "cpv": 0.021882,
      "cpe": 0.189139,
      "saveRate": 0.0,
      "shareRate": 9.9e-05,
      "hookRate": 0.046068,
      "engRate": 0.120713,
      "image": null,
      "verdict": "Profitable"
    },
    {
      "title": "Testimonial_Kedar Lele Marathi",
      "format": "Reel",
      "bucket": "Testimonial",
      "objective": "Engagement",
      "date": "2026-06-18",
      "month": "Jun 2026",
      "boosted": true,
      "spend": 461.57,
      "reach": 12151.0,
      "views": 16640.0,
      "engagements": 1745.0,
      "saves": 1.0,
      "shares": 4.0,
      "follows": 0.0,
      "likes": 865.0,
      "comments": 0.0,
      "status": "Inactive",
      "cpv": 0.027739,
      "cpe": 0.26451,
      "saveRate": 8.2e-05,
      "shareRate": 0.000329,
      "hookRate": 0.071846,
      "engRate": 0.14361,
      "image": null,
      "verdict": "Loss-making"
    },
    {
      "title": "Proposition_Bulky Catalogs",
      "format": "Reel",
      "bucket": "Proposition",
      "objective": "Engagement",
      "date": "2026-01-30",
      "month": "Jan 2026",
      "boosted": true,
      "spend": 451.04,
      "reach": 19617.0,
      "views": 21417.0,
      "engagements": 6323.0,
      "saves": 0.0,
      "shares": 18.0,
      "follows": 0.0,
      "likes": 4120.0,
      "comments": 1.0,
      "status": "Inactive",
      "cpv": 0.02106,
      "cpe": 0.071333,
      "saveRate": 0.0,
      "shareRate": 0.000918,
      "hookRate": 0.110363,
      "engRate": 0.322322,
      "image": null,
      "verdict": "Profitable"
    },
    {
      "title": "Testimonial_Nitin Nair",
      "format": "Reel",
      "bucket": "Testimonial",
      "objective": "Engagement",
      "date": "2026-04-29",
      "month": "Apr 2026",
      "boosted": true,
      "spend": 433.35,
      "reach": 8669.0,
      "views": 12096.0,
      "engagements": 1469.0,
      "saves": 1.0,
      "shares": 6.0,
      "follows": 0.0,
      "likes": 887.0,
      "comments": 1.0,
      "status": "Inactive",
      "cpv": 0.035826,
      "cpe": 0.294997,
      "saveRate": 0.000115,
      "shareRate": 0.000692,
      "hookRate": 0.06529,
      "engRate": 0.169454,
      "image": "images/Testimonial_NitinNair.png",
      "verdict": "Loss-making"
    },
    {
      "title": "Testimonial_Sowmya Motorised Curtains",
      "format": "Reel",
      "bucket": "Testimonial",
      "objective": "Engagement",
      "date": "2026-04-29",
      "month": "Apr 2026",
      "boosted": true,
      "spend": 431.89,
      "reach": 7430.0,
      "views": 9592.0,
      "engagements": 1270.0,
      "saves": 0.0,
      "shares": 3.0,
      "follows": 0.0,
      "likes": 883.0,
      "comments": 0.0,
      "status": "Inactive",
      "cpv": 0.045026,
      "cpe": 0.340071,
      "saveRate": 0.0,
      "shareRate": 0.000404,
      "hookRate": 0.051548,
      "engRate": 0.170929,
      "image": null,
      "verdict": "Loss-making"
    },
    {
      "title": "Testimonial_Harshit",
      "format": "Reel",
      "bucket": "Testimonial",
      "objective": "Engagement",
      "date": "2026-04-06",
      "month": "Apr 2026",
      "boosted": true,
      "spend": 426.28,
      "reach": 12249.0,
      "views": 17044.0,
      "engagements": 2262.0,
      "saves": 1.0,
      "shares": 6.0,
      "follows": 1.0,
      "likes": 1401.0,
      "comments": 0.0,
      "status": "Inactive",
      "cpv": 0.025011,
      "cpe": 0.188453,
      "saveRate": 8.2e-05,
      "shareRate": 0.00049,
      "hookRate": 0.069312,
      "engRate": 0.184668,
      "image": "images/Testimonial_Harshit.png",
      "verdict": "Profitable"
    },
    {
      "title": "Testimonial_Chaitanya Desai",
      "format": "Reel",
      "bucket": "Testimonial",
      "objective": "Engagement",
      "date": "2026-05-28",
      "month": "May 2026",
      "boosted": true,
      "spend": 420.91,
      "reach": 11273.0,
      "views": 14716.0,
      "engagements": 1886.0,
      "saves": 1.0,
      "shares": 3.0,
      "follows": 0.0,
      "likes": 934.0,
      "comments": 1.0,
      "status": "Inactive",
      "cpv": 0.028602,
      "cpe": 0.223176,
      "saveRate": 8.9e-05,
      "shareRate": 0.000266,
      "hookRate": 0.083385,
      "engRate": 0.167302,
      "image": null,
      "verdict": "Broke even"
    },
    {
      "title": "Proposition_Reaction",
      "format": "Reel",
      "bucket": "Proposition",
      "objective": "Engagement",
      "date": "2026-03-05",
      "month": "Mar 2026",
      "boosted": true,
      "spend": 418.94,
      "reach": 18353.0,
      "views": 20364.0,
      "engagements": 6388.0,
      "saves": 1.0,
      "shares": 16.0,
      "follows": 0.0,
      "likes": 2158.0,
      "comments": 0.0,
      "status": "Inactive",
      "cpv": 0.020573,
      "cpe": 0.065582,
      "saveRate": 5.4e-05,
      "shareRate": 0.000872,
      "hookRate": 0.228682,
      "engRate": 0.348063,
      "image": null,
      "verdict": "Profitable"
    },
    {
      "title": "Testimonial_Sowmya Kids Room",
      "format": "Reel",
      "bucket": "Testimonial",
      "objective": "Engagement",
      "date": "2026-04-06",
      "month": "Apr 2026",
      "boosted": true,
      "spend": 413.88,
      "reach": 13302.0,
      "views": 19196.0,
      "engagements": 1834.0,
      "saves": 0.0,
      "shares": 7.0,
      "follows": 0.0,
      "likes": 1066.0,
      "comments": 0.0,
      "status": "Inactive",
      "cpv": 0.021561,
      "cpe": 0.225671,
      "saveRate": 0.0,
      "shareRate": 0.000526,
      "hookRate": 0.057209,
      "engRate": 0.137874,
      "image": null,
      "verdict": "Profitable"
    },
    {
      "title": "Proposition_Pretty Little Baby Trend",
      "format": "Reel",
      "bucket": "Proposition",
      "objective": "Engagement",
      "date": "2026-02-20",
      "month": "Feb 2026",
      "boosted": true,
      "spend": 401.74,
      "reach": 13713.0,
      "views": 14478.0,
      "engagements": 1959.0,
      "saves": 0.0,
      "shares": 3.0,
      "follows": 1.0,
      "likes": 932.0,
      "comments": 0.0,
      "status": "Inactive",
      "cpv": 0.027748,
      "cpe": 0.205074,
      "saveRate": 0.0,
      "shareRate": 0.000219,
      "hookRate": 0.074309,
      "engRate": 0.142857,
      "image": null,
      "verdict": "Broke even"
    },
    {
      "title": "Proposition_Nimisha Billboard",
      "format": "Reel",
      "bucket": "Proposition",
      "objective": "Engagement",
      "date": "2026-02-20",
      "month": "Feb 2026",
      "boosted": true,
      "spend": 399.67,
      "reach": 8137.0,
      "views": 8665.0,
      "engagements": 1949.0,
      "saves": 0.0,
      "shares": 9.0,
      "follows": 0.0,
      "likes": 1286.0,
      "comments": 0.0,
      "status": "Inactive",
      "cpv": 0.046125,
      "cpe": 0.205064,
      "saveRate": 0.0,
      "shareRate": 0.001106,
      "hookRate": 0.080005,
      "engRate": 0.239523,
      "image": null,
      "verdict": "Broke even"
    },
    {
      "title": "Testimonial_Sowmya Master Bedroom",
      "format": "Reel",
      "bucket": "Testimonial",
      "objective": "Traffic",
      "date": "2026-04-29",
      "month": "Apr 2026",
      "boosted": true,
      "spend": 399.6,
      "reach": 13536.0,
      "views": 13956.0,
      "engagements": 895.0,
      "saves": 3.0,
      "shares": 1.0,
      "follows": 2.0,
      "likes": 26.0,
      "comments": 0.0,
      "status": "Inactive",
      "cpv": 0.028633,
      "cpe": 0.44648,
      "saveRate": 0.000222,
      "shareRate": 7.4e-05,
      "hookRate": 0.058806,
      "engRate": 0.06612,
      "image": null,
      "verdict": "Loss-making"
    },
    {
      "title": "Testimonial_Renu Bedi",
      "format": "Reel",
      "bucket": "Testimonial",
      "objective": "Traffic",
      "date": "2026-05-17",
      "month": "May 2026",
      "boosted": true,
      "spend": 398.06,
      "reach": 17266.0,
      "views": 17941.0,
      "engagements": 2656.0,
      "saves": 4.0,
      "shares": 8.0,
      "follows": 12.0,
      "likes": 48.0,
      "comments": 0.0,
      "status": "Inactive",
      "cpv": 0.022187,
      "cpe": 0.149872,
      "saveRate": 0.000232,
      "shareRate": 0.000463,
      "hookRate": 0.139349,
      "engRate": 0.153828,
      "image": null,
      "verdict": "Profitable"
    },
    {
      "title": "Static_Text Testimonial Apoorva",
      "format": "Static",
      "bucket": "Static",
      "objective": "Traffic",
      "date": "2026-04-28",
      "month": "Apr 2026",
      "boosted": true,
      "spend": 397.93,
      "reach": 42654.0,
      "views": 0.0,
      "engagements": 662.0,
      "saves": 0.0,
      "shares": 4.0,
      "follows": 2.0,
      "likes": 52.0,
      "comments": 0.0,
      "status": "Inactive",
      "cpv": null,
      "cpe": 0.601103,
      "saveRate": 0.0,
      "shareRate": 9.4e-05,
      "hookRate": null,
      "engRate": 0.01552,
      "image": "images/Testimonial_Apoorva.png",
      "verdict": "Loss-making"
    },
    {
      "title": "Testimonial_Kashbi",
      "format": "Reel",
      "bucket": "Testimonial",
      "objective": "Engagement",
      "date": "2026-04-06",
      "month": "Apr 2026",
      "boosted": true,
      "spend": 281.15,
      "reach": 9423.0,
      "views": 13289.0,
      "engagements": 1406.0,
      "saves": 0.0,
      "shares": 2.0,
      "follows": 0.0,
      "likes": 821.0,
      "comments": 0.0,
      "status": "Inactive",
      "cpv": 0.021157,
      "cpe": 0.199964,
      "saveRate": 0.0,
      "shareRate": 0.000212,
      "hookRate": 0.061658,
      "engRate": 0.149209,
      "image": "images/Testimonial_Kashbi.png",
      "verdict": "Profitable"
    },
    {
      "title": "Expert Opinion_Curtain Care Tips",
      "format": "Reel",
      "bucket": "Expert Opinion",
      "objective": "Engagement",
      "date": "2025-10-07",
      "month": "Oct 2025",
      "boosted": true,
      "spend": 274.38,
      "reach": 20802.0,
      "views": 20197.0,
      "engagements": 7337.0,
      "saves": 0.0,
      "shares": 2.0,
      "follows": 1.0,
      "likes": 4551.0,
      "comments": 0.0,
      "status": "Inactive",
      "cpv": 0.013585,
      "cpe": 0.037397,
      "saveRate": 0.0,
      "shareRate": 9.6e-05,
      "hookRate": 0.133353,
      "engRate": 0.352706,
      "image": null,
      "verdict": "Profitable"
    },
    {
      "title": "Proposition_Shorter Version.V3",
      "format": "Reel",
      "bucket": "Proposition",
      "objective": "Engagement",
      "date": "2026-04-07",
      "month": "Apr 2026",
      "boosted": true,
      "spend": 229.35,
      "reach": 4315.0,
      "views": 4942.0,
      "engagements": 909.0,
      "saves": 0.0,
      "shares": 5.0,
      "follows": 0.0,
      "likes": 506.0,
      "comments": 0.0,
      "status": "Inactive",
      "cpv": 0.046408,
      "cpe": 0.25231,
      "saveRate": 0.0,
      "shareRate": 0.001159,
      "hookRate": 0.091541,
      "engRate": 0.21066,
      "image": null,
      "verdict": "Broke even"
    },
    {
      "title": "Fast Reel_Why Choose D'Moksha Curtains?",
      "format": "Reel",
      "bucket": "Fast Reel",
      "objective": "Traffic",
      "date": "2026-05-06",
      "month": "May 2026",
      "boosted": true,
      "spend": 199.99,
      "reach": 11408.0,
      "views": 11146.0,
      "engagements": 445.0,
      "saves": 0.0,
      "shares": 1.0,
      "follows": 1.0,
      "likes": 14.0,
      "comments": 0.0,
      "status": "Inactive",
      "cpv": 0.017943,
      "cpe": 0.449416,
      "saveRate": 0.0,
      "shareRate": 8.8e-05,
      "hookRate": 0.035151,
      "engRate": 0.039008,
      "image": null,
      "verdict": "Broke even"
    },
    {
      "title": "Testimonial_Sowmya Final Byte",
      "format": "Reel",
      "bucket": "Testimonial",
      "objective": "Traffic",
      "date": "2026-04-29",
      "month": "Apr 2026",
      "boosted": true,
      "spend": 199.95,
      "reach": 11854.0,
      "views": 11771.0,
      "engagements": 525.0,
      "saves": 0.0,
      "shares": 1.0,
      "follows": 2.0,
      "likes": 11.0,
      "comments": 0.0,
      "status": "Inactive",
      "cpv": 0.016987,
      "cpe": 0.380857,
      "saveRate": 0.0,
      "shareRate": 8.4e-05,
      "hookRate": 0.039902,
      "engRate": 0.044289,
      "image": null,
      "verdict": "Broke even"
    },
    {
      "title": "Carousel_Sparsh",
      "format": "Carousel",
      "bucket": "Carousel",
      "objective": "Traffic",
      "date": "2026-04-30",
      "month": "Apr 2026",
      "boosted": true,
      "spend": 199.95,
      "reach": 25095.0,
      "views": 0.0,
      "engagements": 255.0,
      "saves": 1.0,
      "shares": 0.0,
      "follows": 2.0,
      "likes": 46.0,
      "comments": 0.0,
      "status": "Inactive",
      "cpv": null,
      "cpe": 0.784118,
      "saveRate": 4e-05,
      "shareRate": 0.0,
      "hookRate": null,
      "engRate": 0.010161,
      "image": null,
      "verdict": "Loss-making"
    },
    {
      "title": "AI Reel_Motorised Curtains",
      "format": "Reel",
      "bucket": "AI Reel",
      "objective": "Traffic",
      "date": "2026-05-06",
      "month": "May 2026",
      "boosted": true,
      "spend": 199.92,
      "reach": 11065.0,
      "views": 10973.0,
      "engagements": 586.0,
      "saves": 0.0,
      "shares": 4.0,
      "follows": 0.0,
      "likes": 11.0,
      "comments": 0.0,
      "status": "Inactive",
      "cpv": 0.018219,
      "cpe": 0.34116,
      "saveRate": 0.0,
      "shareRate": 0.000362,
      "hookRate": 0.048712,
      "engRate": 0.05296,
      "image": null,
      "verdict": "Broke even"
    },
    {
      "title": "Proposition_Stylists with Spot Pricing iPad",
      "format": "Reel",
      "bucket": "Proposition",
      "objective": "Traffic",
      "date": "2026-06-09",
      "month": "Jun 2026",
      "boosted": true,
      "spend": 199.81,
      "reach": 11820.0,
      "views": 11566.0,
      "engagements": 2094.0,
      "saves": 1.0,
      "shares": 6.0,
      "follows": 0.0,
      "likes": 43.0,
      "comments": 0.0,
      "status": "Inactive",
      "cpv": 0.017276,
      "cpe": 0.09542,
      "saveRate": 8.5e-05,
      "shareRate": 0.000508,
      "hookRate": 0.168613,
      "engRate": 0.177157,
      "image": null,
      "verdict": "Profitable"
    },
    {
      "title": "Fast Reel_Unlock Your D'Mokhsa Home",
      "format": "Reel",
      "bucket": "Fast Reel",
      "objective": "Traffic",
      "date": "2026-06-17",
      "month": "Jun 2026",
      "boosted": true,
      "spend": 199.68,
      "reach": 9149.0,
      "views": 8925.0,
      "engagements": 375.0,
      "saves": 1.0,
      "shares": 4.0,
      "follows": 1.0,
      "likes": 27.0,
      "comments": 0.0,
      "status": "Inactive",
      "cpv": 0.022373,
      "cpe": 0.53248,
      "saveRate": 0.000109,
      "shareRate": 0.000437,
      "hookRate": 0.034649,
      "engRate": 0.040988,
      "image": null,
      "verdict": "Broke even"
    },
    {
      "title": "AI Reel_Curtain Based On Favorite Destination",
      "format": "Reel",
      "bucket": "AI Reel",
      "objective": "Traffic",
      "date": "2026-04-28",
      "month": "Apr 2026",
      "boosted": true,
      "spend": 199.66,
      "reach": 10034.0,
      "views": 10101.0,
      "engagements": 705.0,
      "saves": 2.0,
      "shares": 3.0,
      "follows": 1.0,
      "likes": 50.0,
      "comments": 1.0,
      "status": "Inactive",
      "cpv": 0.019766,
      "cpe": 0.283206,
      "saveRate": 0.000199,
      "shareRate": 0.000299,
      "hookRate": 0.061092,
      "engRate": 0.070261,
      "image": null,
      "verdict": "Broke even"
    },
    {
      "title": "AI Reel_Bachpan",
      "format": "Reel",
      "bucket": "AI Reel",
      "objective": "Traffic",
      "date": "2026-05-10",
      "month": "May 2026",
      "boosted": true,
      "spend": 199.46,
      "reach": 9061.0,
      "views": 8375.0,
      "engagements": 557.0,
      "saves": 0.0,
      "shares": 2.0,
      "follows": 0.0,
      "likes": 12.0,
      "comments": 0.0,
      "status": "Inactive",
      "cpv": 0.023816,
      "cpe": 0.358097,
      "saveRate": 0.0,
      "shareRate": 0.000221,
      "hookRate": 0.054519,
      "engRate": 0.061472,
      "image": null,
      "verdict": "Broke even"
    },
    {
      "title": "Propositon_We are bringing your curtain dream vision to life",
      "format": "Reel",
      "bucket": "Proposition",
      "objective": "Traffic",
      "date": "2026-06-03",
      "month": "Jun 2026",
      "boosted": true,
      "spend": 199.41,
      "reach": 12079.0,
      "views": 12381.0,
      "engagements": 1493.0,
      "saves": 6.0,
      "shares": 1.0,
      "follows": 6.0,
      "likes": 34.0,
      "comments": 0.0,
      "status": "Inactive",
      "cpv": 0.016106,
      "cpe": 0.133563,
      "saveRate": 0.000497,
      "shareRate": 8.3e-05,
      "hookRate": 0.113337,
      "engRate": 0.123603,
      "image": null,
      "verdict": "Profitable"
    },
    {
      "title": "AI Reel_Curtain Based On Café Drinks Pt 2",
      "format": "Reel",
      "bucket": "AI Reel",
      "objective": "Traffic",
      "date": "2026-06-03",
      "month": "Jun 2026",
      "boosted": true,
      "spend": 199.36,
      "reach": 11786.0,
      "views": 11819.0,
      "engagements": 484.0,
      "saves": 1.0,
      "shares": 0.0,
      "follows": 1.0,
      "likes": 28.0,
      "comments": 0.0,
      "status": "Inactive",
      "cpv": 0.016868,
      "cpe": 0.411901,
      "saveRate": 8.5e-05,
      "shareRate": 0.0,
      "hookRate": 0.03589,
      "engRate": 0.041066,
      "image": null,
      "verdict": "Broke even"
    },
    {
      "title": "Carousel_White Tones",
      "format": "Carousel",
      "bucket": "Carousel",
      "objective": "Traffic",
      "date": "2026-04-28",
      "month": "Apr 2026",
      "boosted": true,
      "spend": 199.31,
      "reach": 21426.0,
      "views": 0.0,
      "engagements": 255.0,
      "saves": 0.0,
      "shares": 0.0,
      "follows": 2.0,
      "likes": 39.0,
      "comments": 1.0,
      "status": "Inactive",
      "cpv": null,
      "cpe": 0.781608,
      "saveRate": 0.0,
      "shareRate": 0.0,
      "hookRate": null,
      "engRate": 0.011901,
      "image": null,
      "verdict": "Loss-making"
    },
    {
      "title": "Fast Reel_Just A Huge Fan",
      "format": "Reel",
      "bucket": "Fast Reel",
      "objective": "Traffic",
      "date": "2026-06-09",
      "month": "Jun 2026",
      "boosted": true,
      "spend": 199.12,
      "reach": 12564.0,
      "views": 12643.0,
      "engagements": 2364.0,
      "saves": 3.0,
      "shares": 4.0,
      "follows": 3.0,
      "likes": 51.0,
      "comments": 0.0,
      "status": "Inactive",
      "cpv": 0.015749,
      "cpe": 0.08423,
      "saveRate": 0.000239,
      "shareRate": 0.000318,
      "hookRate": 0.17391,
      "engRate": 0.188157,
      "image": null,
      "verdict": "Profitable"
    },
    {
      "title": "Testimonial_Sowmya Bedroom",
      "format": "Reel",
      "bucket": "Testimonial",
      "objective": "Traffic",
      "date": "2026-04-28",
      "month": "Apr 2026",
      "boosted": true,
      "spend": 198.95,
      "reach": 9639.0,
      "views": 9847.0,
      "engagements": 638.0,
      "saves": 0.0,
      "shares": 3.0,
      "follows": 3.0,
      "likes": 20.0,
      "comments": 1.0,
      "status": "Inactive",
      "cpv": 0.020204,
      "cpe": 0.311834,
      "saveRate": 0.0,
      "shareRate": 0.000311,
      "hookRate": 0.05789,
      "engRate": 0.066189,
      "image": null,
      "verdict": "Broke even"
    },
    {
      "title": "Fast Reel_Unseen Hands Behind Your Curtains",
      "format": "Reel",
      "bucket": "Fast Reel",
      "objective": "Traffic",
      "date": "2026-06-17",
      "month": "Jun 2026",
      "boosted": true,
      "spend": 198.64,
      "reach": 19847.0,
      "views": 19963.0,
      "engagements": 1627.0,
      "saves": 1.0,
      "shares": 4.0,
      "follows": 5.0,
      "likes": 36.0,
      "comments": 0.0,
      "status": "Inactive",
      "cpv": 0.00995,
      "cpe": 0.12209,
      "saveRate": 5e-05,
      "shareRate": 0.000202,
      "hookRate": 0.076082,
      "engRate": 0.081977,
      "image": null,
      "verdict": "Profitable"
    },
    {
      "title": "Fast Reel_How Much We Love Our Curtains",
      "format": "Reel",
      "bucket": "Fast Reel",
      "objective": "Traffic",
      "date": "2026-04-28",
      "month": "Apr 2026",
      "boosted": true,
      "spend": 198.61,
      "reach": 3461.0,
      "views": 3605.0,
      "engagements": 751.0,
      "saves": 1.0,
      "shares": 3.0,
      "follows": 8.0,
      "likes": 32.0,
      "comments": 1.0,
      "status": "Inactive",
      "cpv": 0.055093,
      "cpe": 0.264461,
      "saveRate": 0.000289,
      "shareRate": 0.000867,
      "hookRate": 0.183473,
      "engRate": 0.216989,
      "image": null,
      "verdict": "Loss-making"
    },
    {
      "title": "AI Reel_Trending Color Pairings of 2026",
      "format": "Reel",
      "bucket": "AI Reel",
      "objective": "Traffic",
      "date": "2026-04-28",
      "month": "Apr 2026",
      "boosted": true,
      "spend": 198.56,
      "reach": 6255.0,
      "views": 5990.0,
      "engagements": 523.0,
      "saves": 10.0,
      "shares": 3.0,
      "follows": 7.0,
      "likes": 17.0,
      "comments": 0.0,
      "status": "Inactive",
      "cpv": 0.033149,
      "cpe": 0.379656,
      "saveRate": 0.001599,
      "shareRate": 0.00048,
      "hookRate": 0.069704,
      "engRate": 0.083613,
      "image": null,
      "verdict": "Loss-making"
    },
    {
      "title": "AI Reel_You See Fabrics",
      "format": "Reel",
      "bucket": "AI Reel",
      "objective": "Traffic",
      "date": "2026-04-28",
      "month": "Apr 2026",
      "boosted": true,
      "spend": 198.37,
      "reach": 3129.0,
      "views": 3154.0,
      "engagements": 639.0,
      "saves": 6.0,
      "shares": 4.0,
      "follows": 15.0,
      "likes": 24.0,
      "comments": 0.0,
      "status": "Inactive",
      "cpv": 0.062895,
      "cpe": 0.310438,
      "saveRate": 0.001918,
      "shareRate": 0.001278,
      "hookRate": 0.169064,
      "engRate": 0.204219,
      "image": null,
      "verdict": "Loss-making"
    },
    {
      "title": "Proposition_10% to 100%",
      "format": "Reel",
      "bucket": "Proposition",
      "objective": "Traffic",
      "date": "2026-04-28",
      "month": "Apr 2026",
      "boosted": true,
      "spend": 198.31,
      "reach": 11883.0,
      "views": 12164.0,
      "engagements": 774.0,
      "saves": 0.0,
      "shares": 1.0,
      "follows": 4.0,
      "likes": 35.0,
      "comments": 0.0,
      "status": "Inactive",
      "cpv": 0.016303,
      "cpe": 0.256214,
      "saveRate": 0.0,
      "shareRate": 8.4e-05,
      "hookRate": 0.058739,
      "engRate": 0.065135,
      "image": null,
      "verdict": "Profitable"
    },
    {
      "title": "Carousel_Dos and Don'ts Of Curtain Hanging",
      "format": "Carousel",
      "bucket": "Carousel",
      "objective": "Traffic",
      "date": "2026-04-28",
      "month": "Apr 2026",
      "boosted": true,
      "spend": 198.16,
      "reach": 21351.0,
      "views": 0.0,
      "engagements": 276.0,
      "saves": 0.0,
      "shares": 0.0,
      "follows": 2.0,
      "likes": 38.0,
      "comments": 0.0,
      "status": "Inactive",
      "cpv": null,
      "cpe": 0.717971,
      "saveRate": 0.0,
      "shareRate": 0.0,
      "hookRate": null,
      "engRate": 0.012927,
      "image": null,
      "verdict": "Loss-making"
    },
    {
      "title": "Fast Reel_Curtain Ho Gya",
      "format": "Reel",
      "bucket": "Fast Reel",
      "objective": "Traffic",
      "date": "2026-06-09",
      "month": "Jun 2026",
      "boosted": true,
      "spend": 197.95,
      "reach": 13032.0,
      "views": 13119.0,
      "engagements": 3151.0,
      "saves": 1.0,
      "shares": 0.0,
      "follows": 0.0,
      "likes": 59.0,
      "comments": 0.0,
      "status": "Inactive",
      "cpv": 0.015089,
      "cpe": 0.062821,
      "saveRate": 7.7e-05,
      "shareRate": 0.0,
      "hookRate": 0.228745,
      "engRate": 0.241789,
      "image": null,
      "verdict": "Profitable"
    },
    {
      "title": "Topical_Party Reel",
      "format": "Reel",
      "bucket": "Topical",
      "objective": "Traffic",
      "date": "2026-06-09",
      "month": "Jun 2026",
      "boosted": true,
      "spend": 197.38,
      "reach": 4880.0,
      "views": 4842.0,
      "engagements": 1056.0,
      "saves": 0.0,
      "shares": 4.0,
      "follows": 0.0,
      "likes": 138.0,
      "comments": 0.0,
      "status": "Inactive",
      "cpv": 0.040764,
      "cpe": 0.186913,
      "saveRate": 0.0,
      "shareRate": 0.00082,
      "hookRate": 0.17541,
      "engRate": 0.216393,
      "image": null,
      "verdict": "Broke even"
    },
    {
      "title": "Proposition_Process 4x4 Grid",
      "format": "Reel",
      "bucket": "Proposition",
      "objective": "Traffic",
      "date": "2026-05-20",
      "month": "May 2026",
      "boosted": true,
      "spend": 197.24,
      "reach": 6441.0,
      "views": 6838.0,
      "engagements": 1356.0,
      "saves": 4.0,
      "shares": 5.0,
      "follows": 10.0,
      "likes": 33.0,
      "comments": 0.0,
      "status": "Inactive",
      "cpv": 0.028845,
      "cpe": 0.145457,
      "saveRate": 0.000621,
      "shareRate": 0.000776,
      "hookRate": 0.189101,
      "engRate": 0.210526,
      "image": null,
      "verdict": "Broke even"
    },
    {
      "title": "AI Reel_Curtain Based On Weekend Vibe",
      "format": "Reel",
      "bucket": "AI Reel",
      "objective": "Traffic",
      "date": "2026-05-20",
      "month": "May 2026",
      "boosted": true,
      "spend": 196.47,
      "reach": 9276.0,
      "views": 9323.0,
      "engagements": 494.0,
      "saves": 0.0,
      "shares": 2.0,
      "follows": 4.0,
      "likes": 20.0,
      "comments": 0.0,
      "status": "Inactive",
      "cpv": 0.021074,
      "cpe": 0.397713,
      "saveRate": 0.0,
      "shareRate": 0.000216,
      "hookRate": 0.046248,
      "engRate": 0.053256,
      "image": null,
      "verdict": "Broke even"
    },
    {
      "title": "Fast Reel_Clock It",
      "format": "Reel",
      "bucket": "Fast Reel",
      "objective": "Traffic",
      "date": "2026-05-28",
      "month": "May 2026",
      "boosted": true,
      "spend": 196.11,
      "reach": 7480.0,
      "views": 8020.0,
      "engagements": 4813.0,
      "saves": 4.0,
      "shares": 13.0,
      "follows": 28.0,
      "likes": 37.0,
      "comments": 0.0,
      "status": "Inactive",
      "cpv": 0.024453,
      "cpe": 0.040746,
      "saveRate": 0.000535,
      "shareRate": 0.001738,
      "hookRate": 0.568449,
      "engRate": 0.643449,
      "image": null,
      "verdict": "Profitable"
    },
    {
      "title": "Proposition_Before vs After vs Result",
      "format": "Reel",
      "bucket": "Proposition",
      "objective": "Traffic",
      "date": "2026-05-16",
      "month": "May 2026",
      "boosted": true,
      "spend": 160.45,
      "reach": 8397.0,
      "views": 8213.0,
      "engagements": 521.0,
      "saves": 0.0,
      "shares": 1.0,
      "follows": 1.0,
      "likes": 16.0,
      "comments": 0.0,
      "status": "Inactive",
      "cpv": 0.019536,
      "cpe": 0.307965,
      "saveRate": 0.0,
      "shareRate": 0.000119,
      "hookRate": 0.056211,
      "engRate": 0.062046,
      "image": null,
      "verdict": "Broke even"
    },
    {
      "title": "AI Reel_Curtain Based On Favorite Season",
      "format": "Reel",
      "bucket": "AI Reel",
      "objective": "Traffic",
      "date": "2026-05-16",
      "month": "May 2026",
      "boosted": true,
      "spend": 160.21,
      "reach": 3442.0,
      "views": 3433.0,
      "engagements": 321.0,
      "saves": 1.0,
      "shares": 2.0,
      "follows": 3.0,
      "likes": 26.0,
      "comments": 0.0,
      "status": "Inactive",
      "cpv": 0.046668,
      "cpe": 0.499097,
      "saveRate": 0.000291,
      "shareRate": 0.000581,
      "hookRate": 0.080186,
      "engRate": 0.09326,
      "image": null,
      "verdict": "Loss-making"
    },
    {
      "title": "Testimonial_Apoorva",
      "format": "Reel",
      "bucket": "Testimonial",
      "objective": "Engagement",
      "date": "2025-11-10",
      "month": "Nov 2025",
      "boosted": true,
      "spend": 114.02,
      "reach": 4640.0,
      "views": 4727.0,
      "engagements": 2289.0,
      "saves": 0.0,
      "shares": 0.0,
      "follows": 0.0,
      "likes": 22.0,
      "comments": 0.0,
      "status": "Inactive",
      "cpv": 0.024121,
      "cpe": 0.049812,
      "saveRate": 0.0,
      "shareRate": 0.0,
      "hookRate": 0.488147,
      "engRate": 0.493319,
      "image": null,
      "verdict": "Profitable"
    },
    {
      "title": "Expert Opinion_Natural vs Man-Made Fabric",
      "format": "Reel",
      "bucket": "Expert Opinion",
      "objective": "Engagement",
      "date": "2026-06-25",
      "month": "Jun 2026",
      "boosted": true,
      "spend": 47.94,
      "reach": 1253.0,
      "views": 1228.0,
      "engagements": 239.0,
      "saves": 0.0,
      "shares": 0.0,
      "follows": 0.0,
      "likes": 163.0,
      "comments": 0.0,
      "status": "Active",
      "cpv": 0.039039,
      "cpe": 0.200586,
      "saveRate": 0.0,
      "shareRate": 0.0,
      "hookRate": 0.060654,
      "engRate": 0.190742,
      "image": null,
      "verdict": "Broke even"
    },
    {
      "title": "Expert Opinion: Curtain Care Instructions",
      "format": "Reel",
      "bucket": "Expert Opinion",
      "objective": "Engagement",
      "date": "2025-10-29",
      "month": "Oct 2025",
      "boosted": true,
      "spend": 39.54,
      "reach": 1753.0,
      "views": 1742.0,
      "engagements": 729.0,
      "saves": 0.0,
      "shares": 0.0,
      "follows": 0.0,
      "likes": 47.0,
      "comments": 0.0,
      "status": "Inactive",
      "cpv": 0.022698,
      "cpe": 0.054239,
      "saveRate": 0.0,
      "shareRate": 0.0,
      "hookRate": 0.388477,
      "engRate": 0.415859,
      "image": null,
      "verdict": "Profitable"
    },
    {
      "title": "AI Reel_Accent Chairs Spotlight",
      "format": "Reel",
      "bucket": "AI Reel",
      "objective": "Traffic",
      "date": "2026-06-25",
      "month": "Jun 2026",
      "boosted": true,
      "spend": 21.3,
      "reach": 363.0,
      "views": 374.0,
      "engagements": 50.0,
      "saves": 0.0,
      "shares": 0.0,
      "follows": 0.0,
      "likes": 3.0,
      "comments": 0.0,
      "status": "Active",
      "cpv": 0.056952,
      "cpe": 0.426,
      "saveRate": 0.0,
      "shareRate": 0.0,
      "hookRate": 0.115702,
      "engRate": 0.137741,
      "image": null,
      "verdict": "Loss-making"
    },
    {
      "title": "Fast Reel_Jutsu Trend",
      "format": "Reel",
      "bucket": "Fast Reel",
      "objective": "Traffic",
      "date": "2026-06-25",
      "month": "Jun 2026",
      "boosted": true,
      "spend": 20.41,
      "reach": 571.0,
      "views": 551.0,
      "engagements": 135.0,
      "saves": 0.0,
      "shares": 1.0,
      "follows": 0.0,
      "likes": 5.0,
      "comments": 0.0,
      "status": "Active",
      "cpv": 0.037042,
      "cpe": 0.151185,
      "saveRate": 0.0,
      "shareRate": 0.001751,
      "hookRate": 0.211909,
      "engRate": 0.236427,
      "image": null,
      "verdict": "Broke even"
    },
    {
      "title": "Fast Reel_Don't Post Work, Post Working",
      "format": "Reel",
      "bucket": "Fast Reel",
      "objective": "Traffic",
      "date": "2026-06-25",
      "month": "Jun 2026",
      "boosted": true,
      "spend": 16.49,
      "reach": 700.0,
      "views": 662.0,
      "engagements": 187.0,
      "saves": 0.0,
      "shares": 0.0,
      "follows": 0.0,
      "likes": 6.0,
      "comments": 0.0,
      "status": "Active",
      "cpv": 0.024909,
      "cpe": 0.088182,
      "saveRate": 0.0,
      "shareRate": 0.0,
      "hookRate": 0.242857,
      "engRate": 0.267143,
      "image": null,
      "verdict": "Profitable"
    },
    {
      "title": "Proposition_There is magic in the process",
      "format": "Reel",
      "bucket": "Proposition",
      "objective": "Traffic",
      "date": "2026-06-25",
      "month": "Jun 2026",
      "boosted": true,
      "spend": 15.7,
      "reach": 863.0,
      "views": 839.0,
      "engagements": 51.0,
      "saves": 0.0,
      "shares": 0.0,
      "follows": 0.0,
      "likes": 3.0,
      "comments": 0.0,
      "status": "Active",
      "cpv": 0.018713,
      "cpe": 0.307843,
      "saveRate": 0.0,
      "shareRate": 0.0,
      "hookRate": 0.053302,
      "engRate": 0.059096,
      "image": null,
      "verdict": "Broke even"
    },
    {
      "title": "Fast Reel_A Little Bit Of This Factory BTS",
      "format": "Reel",
      "bucket": "Fast Reel",
      "objective": "Traffic",
      "date": "2026-06-25",
      "month": "Jun 2026",
      "boosted": true,
      "spend": 11.67,
      "reach": 327.0,
      "views": 317.0,
      "engagements": 113.0,
      "saves": 0.0,
      "shares": 2.0,
      "follows": 1.0,
      "likes": 3.0,
      "comments": 0.0,
      "status": "Active",
      "cpv": 0.036814,
      "cpe": 0.103274,
      "saveRate": 0.0,
      "shareRate": 0.006116,
      "hookRate": 0.314985,
      "engRate": 0.345566,
      "image": null,
      "verdict": "Broke even"
    },
    {
      "title": "Testimonial_Nitin",
      "format": "Reel",
      "bucket": "Testimonial",
      "objective": "Engagement",
      "date": "2025-11-10",
      "month": "Nov 2025",
      "boosted": true,
      "spend": 0.22,
      "reach": 13.0,
      "views": 13.0,
      "engagements": 9.0,
      "saves": 0.0,
      "shares": 0.0,
      "follows": 0.0,
      "likes": 1.0,
      "comments": 0.0,
      "status": "Inactive",
      "cpv": 0.016923,
      "cpe": 0.024444,
      "saveRate": 0.0,
      "shareRate": 0.0,
      "hookRate": 0.615385,
      "engRate": 0.692308,
      "image": "images/Testimonial_Nitin.png",
      "verdict": "Profitable"
    }
  ]
}